selfpkg/__init__.py
selfpkg/farewell.py
selfpkg/greeting.py
selfpkg-0.0.2.dist-info/METADATA
selfpkg-0.0.2.dist-info/WHEEL
selfpkg-0.0.2.dist-info/top_level.txt
selfpkg-0.0.2.dist-info/RECORD
