Metadata-Version: 2.1
Name: selfpkg
Version: 0.0.2
Summary: Just for self-learning publishing from GitHub!
Author-email: Shao-Lun Huang <simon.linux7@gmail.com>
License: MIT
Requires-Python: >=3.11
